nostro_mt5_manager_v1/__init__.py
nostro_mt5_manager_v1/dealer_sink.py
nostro_mt5_manager_v1/manager.py
nostro_mt5_manager_v1/manager_helper.py
nostro_mt5_manager_v1-0.0.7.dist-info/METADATA
nostro_mt5_manager_v1-0.0.7.dist-info/WHEEL
nostro_mt5_manager_v1-0.0.7.dist-info/licenses/LICENSE.md
nostro_mt5_manager_v1-0.0.7.dist-info/RECORD
