Metadata-Version: 2.4
Name: nostro_mt5_manager_v1
Version: 0.0.7
Summary: nostro mt5 manager
Project-URL: homepage, https://python_mt5_manager.vercel.app
Project-URL: documentation, https://python_mt5_manager.gitbook.io/docs
Project-URL: repository, https://github.com/krunaldodiya/python_mt5_manager
Author-email: Nostro Python <nostropython@gmail.com>
License: MIT
License-File: LICENSE.md
Requires-Dist: mt5manager>=5.0.4803
Provides-Extra: dev
Requires-Dist: cython>=3.0.11; extra == 'dev'
Requires-Dist: mypy>=1.11.2; extra == 'dev'
Requires-Dist: pytest>=8.3.2; extra == 'dev'
Requires-Dist: twine>=5.1.1; extra == 'dev'
Requires-Dist: wheel>=0.44.0; extra == 'dev'
